composablesoup/__init__.py
composablesoup/soup.py
composablesoup-0.2.4.dist-info/WHEEL
composablesoup-0.2.4.dist-info/METADATA
composablesoup-0.2.4.dist-info/RECORD
